{
  "$schema": "https://developer.microsoft.com/json-schemas/fabric/item/report/definition/visualContainer/2.3.0/schema.json",
  "name": "fd2702cf76ac2ced9e0f",
  "position": {
    "x": 581.8201309904689,
    "y": 13.722172900718606,
    "z": 1000,
    "height": 326.58771503710284,
    "width": 292.28228278530628,
    "tabOrder": 1000
  },
  "visual": {
    "visualType": "tableEx",
    "query": {
      "queryState": {
        "Values": {
          "projections": [
            {
              "field": {
                "Column": {
                  "Expression": {
                    "SourceRef": {
                      "Entity": "netflix_titles"
                    }
                  },
                  "Property": "country"
                }
              },
              "queryRef": "netflix_titles.country",
              "nativeQueryRef": "Country",
              "displayName": "Country"
            },
            {
              "field": {
                "Column": {
                  "Expression": {
                    "SourceRef": {
                      "Entity": "netflix_titles"
                    }
                  },
                  "Property": "type"
                }
              },
              "queryRef": "netflix_titles.type",
              "nativeQueryRef": "Content-type",
              "displayName": "Content-type"
            },
            {
              "field": {
                "Aggregation": {
                  "Expression": {
                    "Column": {
                      "Expression": {
                        "SourceRef": {
                          "Entity": "netflix_titles"
                        }
                      },
                      "Property": "country"
                    }
                  },
                  "Function": 5
                }
              },
              "queryRef": "CountNonNull(netflix_titles.country)",
              "nativeQueryRef": "Count of country1",
              "displayName": "Contribution"
            }
          ]
        }
      },
      "sortDefinition": {
        "sort": [
          {
            "field": {
              "Column": {
                "Expression": {
                  "SourceRef": {
                    "Entity": "netflix_titles"
                  }
                },
                "Property": "country"
              }
            },
            "direction": "Ascending"
          }
        ]
      }
    },
    "objects": {
      "columnHeaders": [
        {
          "properties": {
            "autoSizeColumnWidth": {
              "expr": {
                "Literal": {
                  "Value": "false"
                }
              }
            }
          }
        }
      ],
      "columnWidth": [
        {
          "properties": {
            "value": {
              "expr": {
                "Literal": {
                  "Value": "107D"
                }
              }
            }
          },
          "selector": {
            "metadata": "netflix_titles.country"
          }
        },
        {
          "properties": {
            "value": {
              "expr": {
                "Literal": {
                  "Value": "62D"
                }
              }
            }
          },
          "selector": {
            "metadata": "netflix_titles.type"
          }
        },
        {
          "properties": {
            "value": {
              "expr": {
                "Literal": {
                  "Value": "111D"
                }
              }
            }
          },
          "selector": {
            "metadata": "CountNonNull(netflix_titles.country)"
          }
        }
      ]
    },
    "drillFilterOtherVisuals": true
  },
  "filterConfig": {
    "filters": [
      {
        "name": "2cea740d303708f2359c",
        "field": {
          "Column": {
            "Expression": {
              "SourceRef": {
                "Entity": "netflix_titles"
              }
            },
            "Property": "type"
          }
        },
        "type": "Categorical",
        "filter": {
          "Version": 2,
          "From": [
            {
              "Name": "n",
              "Entity": "netflix_titles",
              "Type": 0
            }
          ],
          "Where": [
            {
              "Condition": {
                "Not": {
                  "Expression": {
                    "In": {
                      "Expressions": [
                        {
                          "Column": {
                            "Expression": {
                              "SourceRef": {
                                "Source": "n"
                              }
                            },
                            "Property": "type"
                          }
                        }
                      ],
                      "Values": [
                        [
                          {
                            "Literal": {
                              "Value": "''"
                            }
                          }
                        ],
                        [
                          {
                            "Literal": {
                              "Value": "'William Wyler'"
                            }
                          }
                        ]
                      ]
                    }
                  }
                }
              }
            }
          ]
        },
        "objects": {
          "general": [
            {
              "properties": {
                "isInvertedSelectionMode": {
                  "expr": {
                    "Literal": {
                      "Value": "true"
                    }
                  }
                }
              }
            }
          ]
        }
      }
    ]
  }
}